{
  "recibidas": {
    "n": 324,
    "l": "TRES DOS CUATRO"
  },
  "sobrantes": {
    "n": 115,
    "l": "UNO UNO CINCO"
  },
  "usadas": {
    "n": 209,
    "l": "DOS CERO NOVE"
  },
  "total_votantes": {
    "n": 209,
    "l": "DOS CERO NOVE"
  },
  "partido_dc": {
    "n": 1,
    "l": "CERO CERO UNO"
  },
  "partido_libre": {
    "n": 49,
    "l": "CERO CUATRO NOVE"
  },
  "partido_pinu": {
    "n": 1,
    "l": "CERO CERO UNO"
  },
  "partido_plh": {
    "n": 38,
    "l": "CERO TRES OCHO"
  },
  "partido_pnh": {
    "n": 119,
    "l": "UNO UNO NOVE"
  },
  "en_blanco": {
    "n": 0,
    "l": "CERO CERO CERO"
  },
  "nulos": {
    "n": 1,
    "l": "CERO CERO UNO"
  },
  "gran_total": {
    "n": 209,
    "l": "DOS CERO NOVE"
  }
}