{
  "recibidas": {
    "n": 185,
    "l": "uno ocho cinco"
  },
  "sobrantes": {
    "n": 32,
    "l": "cero tres"
  },
  "usadas": {
    "n": 153,
    "l": "uno cinco"
  },
  "total_votantes": {
    "n": 153,
    "l": "uno cinco"
  },
  "partido_dc": {
    "n": 0,
    "l": "cero cero cero"
  },
  "partido_libre": {
    "n": 59,
    "l": "cero cinco"
  },
  "partido_pinu": {
    "n": 0,
    "l": "cero cero cero"
  },
  "partido_plh": {
    "n": 36,
    "l": "cero tres"
  },
  "partido_pnh": {
    "n": 56,
    "l": "cero cinco"
  },
  "en_blanco": {
    "n": 2,
    "l": "cero cero"
  },
  "nulos": {
    "n": 0,
    "l": "cero cero cero"
  },
  "gran_total": {
    "n": 153,
    "l": "uno cinco"
  }
}