{
  "recibidas": {
    "n": "223",
    "l": "Dos Dos Tres"
  },
  "sobrantes": {
    "n": "039",
    "l": "Cero Tres Nueve"
  },
  "usadas": {
    "n": "184",
    "l": "Uno Ocho Cuatro"
  },
  "total_votantes": {
    "n": "184",
    "l": "Uno Ocho Cuatro"
  },
  "partido_dc": {
    "n": "000",
    "l": "Cero Cero Cero"
  },
  "partido_libre": {
    "n": "096",
    "l": "Cero Nueve Seis"
  },
  "partido_pinu": {
    "n": "001",
    "l": "Cero Cero Uno"
  },
  "partido_plh": {
    "n": "038",
    "l": "Cero Tres Ocho"
  },
  "partido_pnh": {
    "n": "038",
    "l": "Cero Tres Ocho"
  },
  "en_blanco": {
    "n": "002",
    "l": "Cero Cero Dos"
  },
  "nulos": {
    "n": "009",
    "l": "Cero Cero Nueve"
  },
  "gran_total": {
    "n": "184",
    "l": "Uno Ocho Cuatro"
  }
}