{
  "recibidas": {
    "n": "254",
    "l": "Dos Cinco Cuatro"
  },
  "sobrantes": {
    "n": "071",
    "l": "Cero Siete Uno"
  },
  "usadas": {
    "n": "183",
    "l": "Uno Ocho Tres"
  },
  "total_votantes": {
    "n": "183",
    "l": "Uno Ocho Tres"
  },
  "partido_dc": {
    "n": "000",
    "l": "Cero Cero Cero"
  },
  "partido_libre": {
    "n": "039",
    "l": "Cero Tres Nueve"
  },
  "partido_pinu": {
    "n": "000",
    "l": "Cero Cero Cero"
  },
  "partido_plh": {
    "n": "061",
    "l": "Cero Seis Uno"
  },
  "partido_pnh": {
    "n": "070",
    "l": "Cero Siete Cero"
  },
  "en_blanco": {
    "n": "005",
    "l": "Cero Cero Cinco"
  },
  "nulos": {
    "n": "008",
    "l": "Cero Cero Ocho"
  },
  "gran_total": {
    "n": "183",
    "l": "Uno Ocho Tres"
  }
}