{
  "recibidas": {
    "n": "347",
    "l": "Tres cuatro siete"
  },
  "sobrantes": {
    "n": "157",
    "l": "Uno cinco siete"
  },
  "usadas": {
    "n": "190",
    "l": "Uno nueve cero"
  },
  "total_votantes": {
    "n": "190",
    "l": "Uno nueve cero"
  },
  "partido_dc": {
    "n": "000",
    "l": "cero cero cero"
  },
  "partido_libre": {
    "n": "039",
    "l": "cero tres nueve"
  },
  "partido_pinu": {
    "n": "003",
    "l": "cero cero tres"
  },
  "partido_plh": {
    "n": "104",
    "l": "uno cero cuatro"
  },
  "partido_pnh": {
    "n": "036",
    "l": "cero tres seis"
  },
  "en_blanco": {
    "n": "003",
    "l": "cero cero tres"
  },
  "nulos": {
    "n": "005",
    "l": "cero cero cinco"
  },
  "gran_total": {
    "n": "190",
    "l": "uno nueve cero"
  }
}