{
  "recibidas": {
    "n": 352,
    "l": "TRES CINCO IDOS"
  },
  "sobrantes": {
    "n": 135,
    "l": "UNO TRES CINCO"
  },
  "usadas": {
    "n": 217,
    "l": "IDOS UNO SIETE"
  },
  "total_votantes": {
    "n": 217,
    "l": "IDOS UNO SIETE"
  },
  "partido_dc": {
    "n": 0,
    "l": "CERO CERO CERO"
  },
  "partido_libre": {
    "n": 18,
    "l": "CERO UNO OCHO"
  },
  "partido_pinu": {
    "n": 0,
    "l": "CERO CERO CERO"
  },
  "partido_plh": {
    "n": 68,
    "l": "CERO SEIS OCHO"
  },
  "partido_pnh": {
    "n": 121,
    "l": "UNO IDOS UNO"
  },
  "en_blanco": {
    "n": 8,
    "l": "CERO CERO OCHO"
  },
  "nulos": {
    "n": 2,
    "l": "CERO CERO DOS"
  },
  "gran_total": {
    "n": 217,
    "l": "IDOS UNO SIETE"
  }
}