{
  "recibidas": {
    "n": 0,
    "l": ""
  },
  "sobrantes": {
    "n": 0,
    "l": ""
  },
  "usadas": {
    "n": 0,
    "l": ""
  },
  "total_votantes": {
    "n": 0,
    "l": ""
  },
  "partido_dc": {
    "n": 0,
    "l": ""
  },
  "partido_libre": {
    "n": 8,
    "l": "Cero Cero Ocho"
  },
  "partido_pinu": {
    "n": 1,
    "l": "Cero Cero Uno"
  },
  "partido_plh": {
    "n": 122,
    "l": "Uno Dos Dos"
  },
  "partido_pnh": {
    "n": 40,
    "l": "Cero Cuatro Cero"
  },
  "en_blanco": {
    "n": 1,
    "l": "Cero Cero Uno"
  },
  "nulos": {
    "n": 3,
    "l": "Cero Cero Tres"
  },
  "gran_total": {
    "n": 175,
    "l": "Uno Siete Cinco"
  }
}