{
  "recibidas": {
    "n": 0,
    "l": ""
  },
  "sobrantes": {
    "n": 65,
    "l": "cero seis cinco"
  },
  "usadas": {
    "n": 6,
    "l": "dos cero seis"
  },
  "total_votantes": {
    "n": 6,
    "l": "dos cero seis"
  },
  "partido_dc": {
    "n": 0,
    "l": "cero cero cero"
  },
  "partido_libre": {
    "n": 26,
    "l": "cero dos seis"
  },
  "partido_pinu": {
    "n": 0,
    "l": "cero cero cero"
  },
  "partido_plh": {
    "n": 0,
    "l": ""
  },
  "partido_pnh": {
    "n": 133,
    "l": "uno tres tres"
  },
  "en_blanco": {
    "n": 4,
    "l": "cero cero cuatro"
  },
  "nulos": {
    "n": 3,
    "l": "cero cero tres"
  },
  "gran_total": {
    "n": 6,
    "l": "dos cero seis"
  }
}