[
  {
    "publicada": 1,
    "numero": 17045,
    "escrutado": true,
    "digitalizado": 1,
    "id_informacion_mesa_corporacion": "01160180203617045",
    "nombre_archivo": "https://elecciones-hnd-publicacion-prod-us-east-1.s3.us-east-1.amazonaws.com/ACTAS/16/1618170450041000.pdf?X-Amz-Algorithm=AWS4-HMAC-SHA256&X-Amz-Credential=AKIATNSYFO5EYDYMH46K%2F20251205%2Fus-east-1%2Fs3%2Faws4_request&X-Amz-Date=20251205T192457Z&X-Amz-Expires=7200&X-Amz-SignedHeaders=host&X-Amz-Signature=85d24224b16b82bd57715fb94b792bf23fbd423e94fb184f93a9d666696c2614",
    "etiquetas": [
      "Divulgada Correctamente",
      "Pendiente de Revisión"
    ]
  },
  {
    "publicada": 1,
    "numero": 17046,
    "escrutado": true,
    "digitalizado": 1,
    "id_informacion_mesa_corporacion": "01160180203617046",
    "nombre_archivo": "https://elecciones-hnd-publicacion-prod-us-east-1.s3.us-east-1.amazonaws.com/ACTAS/16/1618170460041000.pdf?X-Amz-Algorithm=AWS4-HMAC-SHA256&X-Amz-Credential=AKIATNSYFO5EYDYMH46K%2F20251205%2Fus-east-1%2Fs3%2Faws4_request&X-Amz-Date=20251205T192457Z&X-Amz-Expires=7200&X-Amz-SignedHeaders=host&X-Amz-Signature=4bd90ae872bcc74488604bf4aed84835c2174be2f5299d9c8dcded395da12b1e",
    "etiquetas": [
      "Inconsistencia",
      "Pendiente de Revisión"
    ]
  }
]