[
  {
    "publicada": 1,
    "numero": 10463,
    "escrutado": true,
    "digitalizado": 1,
    "id_informacion_mesa_corporacion": "01080010135210463",
    "nombre_archivo": "https://elecciones-hnd-publicacion-prod-us-east-1.s3.us-east-1.amazonaws.com/ACTAS/08/0801104630041000.pdf?X-Amz-Algorithm=AWS4-HMAC-SHA256&X-Amz-Credential=AKIATNSYFO5EYDYMH46K%2F20251206%2Fus-east-1%2Fs3%2Faws4_request&X-Amz-Date=20251206T002755Z&X-Amz-Expires=7200&X-Amz-SignedHeaders=host&X-Amz-Signature=7e577eeacf2678f61e6450bc9982fe15ae52078c2dad867e3068c225a281840e",
    "etiquetas": [
      "Divulgada Correctamente"
    ]
  },
  {
    "publicada": 1,
    "numero": 10464,
    "escrutado": true,
    "digitalizado": 1,
    "id_informacion_mesa_corporacion": "01080010135210464",
    "nombre_archivo": "https://elecciones-hnd-publicacion-prod-us-east-1.s3.us-east-1.amazonaws.com/ACTAS/08/0801104640041000.pdf?X-Amz-Algorithm=AWS4-HMAC-SHA256&X-Amz-Credential=AKIATNSYFO5EYDYMH46K%2F20251206%2Fus-east-1%2Fs3%2Faws4_request&X-Amz-Date=20251206T002755Z&X-Amz-Expires=7200&X-Amz-SignedHeaders=host&X-Amz-Signature=007a8f0e1368729bd66a491d8148e3fee659dfb950d48319d70888eb455f895c",
    "etiquetas": [
      "Inconsistencia"
    ]
  },
  {
    "publicada": 1,
    "numero": 10465,
    "escrutado": true,
    "digitalizado": 1,
    "id_informacion_mesa_corporacion": "01080010135210465",
    "nombre_archivo": "https://elecciones-hnd-publicacion-prod-us-east-1.s3.us-east-1.amazonaws.com/ACTAS/08/0801104650041000.pdf?X-Amz-Algorithm=AWS4-HMAC-SHA256&X-Amz-Credential=AKIATNSYFO5EYDYMH46K%2F20251206%2Fus-east-1%2Fs3%2Faws4_request&X-Amz-Date=20251206T002755Z&X-Amz-Expires=7200&X-Amz-SignedHeaders=host&X-Amz-Signature=e32e3b97493548d46adc2b8751e26fc33f7b8464495cd895702ccd6606c9a3c1",
    "etiquetas": [
      "Divulgada Correctamente"
    ]
  },
  {
    "publicada": 1,
    "numero": 10466,
    "escrutado": true,
    "digitalizado": 1,
    "id_informacion_mesa_corporacion": "01080010135210466",
    "nombre_archivo": "https://elecciones-hnd-publicacion-prod-us-east-1.s3.us-east-1.amazonaws.com/ACTAS/08/0801104660041000.pdf?X-Amz-Algorithm=AWS4-HMAC-SHA256&X-Amz-Credential=AKIATNSYFO5EYDYMH46K%2F20251206%2Fus-east-1%2Fs3%2Faws4_request&X-Amz-Date=20251206T002755Z&X-Amz-Expires=7200&X-Amz-SignedHeaders=host&X-Amz-Signature=b1376790afb3d56a48e01beb041ea887fd8a3f36344c463aca32501a9439cfcf",
    "etiquetas": [
      "Divulgada Correctamente"
    ]
  },
  {
    "publicada": 1,
    "numero": 10467,
    "escrutado": true,
    "digitalizado": 1,
    "id_informacion_mesa_corporacion": "01080010135210467",
    "nombre_archivo": "https://elecciones-hnd-publicacion-prod-us-east-1.s3.us-east-1.amazonaws.com/E14/08/001/01/352/E14_P01_08_001_001_00_352_10467_3833.pdf?X-Amz-Algorithm=AWS4-HMAC-SHA256&X-Amz-Credential=AKIATNSYFO5EYDYMH46K%2F20251206%2Fus-east-1%2Fs3%2Faws4_request&X-Amz-Date=20251206T002755Z&X-Amz-Expires=7200&X-Amz-SignedHeaders=host&X-Amz-Signature=e2460582b22aa93a3f807b1de0cf31ec9040e0e7fee637769d0188105d6d56bf",
    "etiquetas": [
      "Inconsistencia"
    ]
  },
  {
    "publicada": 1,
    "numero": 10468,
    "escrutado": true,
    "digitalizado": 1,
    "id_informacion_mesa_corporacion": "01080010135210468",
    "nombre_archivo": "https://elecciones-hnd-publicacion-prod-us-east-1.s3.us-east-1.amazonaws.com/E14/08/001/01/352/E14_P01_08_001_001_00_352_10468_3833.pdf?X-Amz-Algorithm=AWS4-HMAC-SHA256&X-Amz-Credential=AKIATNSYFO5EYDYMH46K%2F20251206%2Fus-east-1%2Fs3%2Faws4_request&X-Amz-Date=20251206T002755Z&X-Amz-Expires=7200&X-Amz-SignedHeaders=host&X-Amz-Signature=146110dfa44b3ecbc301010de9291abc8b388f1fddab828d501968bf87a8bce5",
    "etiquetas": [
      "Divulgada Correctamente"
    ]
  },
  {
    "publicada": 1,
    "numero": 10469,
    "escrutado": true,
    "digitalizado": 1,
    "id_informacion_mesa_corporacion": "01080010135210469",
    "nombre_archivo": "https://elecciones-hnd-publicacion-prod-us-east-1.s3.us-east-1.amazonaws.com/E14/08/001/01/352/E14_P01_08_001_001_00_352_10469_3833.pdf?X-Amz-Algorithm=AWS4-HMAC-SHA256&X-Amz-Credential=AKIATNSYFO5EYDYMH46K%2F20251206%2Fus-east-1%2Fs3%2Faws4_request&X-Amz-Date=20251206T002755Z&X-Amz-Expires=7200&X-Amz-SignedHeaders=host&X-Amz-Signature=42e7d49e71ab5c20bcf1d7b2a41e6f55355d481ffb4c377239c1c1ad96675638",
    "etiquetas": [
      "Divulgada Correctamente"
    ]
  },
  {
    "publicada": 1,
    "numero": 10470,
    "escrutado": true,
    "digitalizado": 1,
    "id_informacion_mesa_corporacion": "01080010135210470",
    "nombre_archivo": "https://elecciones-hnd-publicacion-prod-us-east-1.s3.us-east-1.amazonaws.com/ACTAS/08/0801104700041000.pdf?X-Amz-Algorithm=AWS4-HMAC-SHA256&X-Amz-Credential=AKIATNSYFO5EYDYMH46K%2F20251206%2Fus-east-1%2Fs3%2Faws4_request&X-Amz-Date=20251206T002755Z&X-Amz-Expires=7200&X-Amz-SignedHeaders=host&X-Amz-Signature=76443800ab4887e78dd833557ebfc5e4c69752d009f8e65eb293da68655611cd",
    "etiquetas": [
      "Divulgada Correctamente"
    ]
  },
  {
    "publicada": 1,
    "numero": 10471,
    "escrutado": true,
    "digitalizado": 1,
    "id_informacion_mesa_corporacion": "01080010135210471",
    "nombre_archivo": "https://elecciones-hnd-publicacion-prod-us-east-1.s3.us-east-1.amazonaws.com/ACTAS/08/0801104710041000.pdf?X-Amz-Algorithm=AWS4-HMAC-SHA256&X-Amz-Credential=AKIATNSYFO5EYDYMH46K%2F20251206%2Fus-east-1%2Fs3%2Faws4_request&X-Amz-Date=20251206T002755Z&X-Amz-Expires=7200&X-Amz-SignedHeaders=host&X-Amz-Signature=47e107b02ca4ea6d1d3ad3f96fdc7990ffa0ecafce44f46657346018a2c7b51a",
    "etiquetas": [
      "Divulgada Correctamente"
    ]
  },
  {
    "publicada": 1,
    "numero": 10472,
    "escrutado": true,
    "digitalizado": 1,
    "id_informacion_mesa_corporacion": "01080010135210472",
    "nombre_archivo": "https://elecciones-hnd-publicacion-prod-us-east-1.s3.us-east-1.amazonaws.com/ACTAS/08/0801104720041000.pdf?X-Amz-Algorithm=AWS4-HMAC-SHA256&X-Amz-Credential=AKIATNSYFO5EYDYMH46K%2F20251206%2Fus-east-1%2Fs3%2Faws4_request&X-Amz-Date=20251206T002755Z&X-Amz-Expires=7200&X-Amz-SignedHeaders=host&X-Amz-Signature=85a28880e0ec0e367ae6e7aaba90a79ce740837bb1a886d4568c7eb60dc6d171",
    "etiquetas": [
      "Divulgada Correctamente"
    ]
  }
]