[
  {
    "publicada": 1,
    "numero": 17233,
    "escrutado": true,
    "digitalizado": 1,
    "id_informacion_mesa_corporacion": "01160230201117233",
    "nombre_archivo": "https://elecciones-hnd-publicacion-prod-us-east-1.s3.us-east-1.amazonaws.com/E14/16/023/02/011/E14_P01_16_023_002_00_011_17233_6832.pdf?X-Amz-Algorithm=AWS4-HMAC-SHA256&X-Amz-Credential=AKIATNSYFO5EYDYMH46K%2F20251205%2Fus-east-1%2Fs3%2Faws4_request&X-Amz-Date=20251205T192529Z&X-Amz-Expires=7200&X-Amz-SignedHeaders=host&X-Amz-Signature=58e5a9665006575deb4270ebac930ced7c3e01b6bc8b5471e131286f7e43f36f",
    "etiquetas": [
      "Inconsistencia"
    ]
  },
  {
    "publicada": 1,
    "numero": 17234,
    "escrutado": true,
    "digitalizado": 1,
    "id_informacion_mesa_corporacion": "01160230201117234",
    "nombre_archivo": "https://elecciones-hnd-publicacion-prod-us-east-1.s3.us-east-1.amazonaws.com/E14/16/023/02/011/E14_P01_16_023_002_00_011_17234_6832.pdf?X-Amz-Algorithm=AWS4-HMAC-SHA256&X-Amz-Credential=AKIATNSYFO5EYDYMH46K%2F20251205%2Fus-east-1%2Fs3%2Faws4_request&X-Amz-Date=20251205T192529Z&X-Amz-Expires=7200&X-Amz-SignedHeaders=host&X-Amz-Signature=8c793490945190a824a0078080d5e1159d1d9b82d411b51b43e75eb648599e84",
    "etiquetas": [
      "Divulgada Correctamente"
    ]
  }
]