[
  {
    "publicada": 1,
    "numero": 667,
    "escrutado": true,
    "digitalizado": 1,
    "id_informacion_mesa_corporacion": "010100701007667",
    "nombre_archivo": "https://elecciones-hnd-publicacion-prod-us-east-1.s3.us-east-1.amazonaws.com/E14/01/007/01/007/E14_P01_01_007_001_00_007_667_0242.pdf?X-Amz-Algorithm=AWS4-HMAC-SHA256&X-Amz-Credential=AKIATNSYFO5EYDYMH46K%2F20251206%2Fus-east-1%2Fs3%2Faws4_request&X-Amz-Date=20251206T044050Z&X-Amz-Expires=7200&X-Amz-SignedHeaders=host&X-Amz-Signature=cf09710e2986877d71f020327652e68ef68db026557d68eb8e1f9902baee0c3b",
    "etiquetas": [
      "Divulgada Correctamente"
    ],
    "needs_download": true
  },
  {
    "publicada": 1,
    "numero": 668,
    "escrutado": true,
    "digitalizado": 1,
    "id_informacion_mesa_corporacion": "010100701007668",
    "nombre_archivo": "https://elecciones-hnd-publicacion-prod-us-east-1.s3.us-east-1.amazonaws.com/E14/01/007/01/007/E14_P01_01_007_001_00_007_668_0242.pdf?X-Amz-Algorithm=AWS4-HMAC-SHA256&X-Amz-Credential=AKIATNSYFO5EYDYMH46K%2F20251206%2Fus-east-1%2Fs3%2Faws4_request&X-Amz-Date=20251206T044050Z&X-Amz-Expires=7200&X-Amz-SignedHeaders=host&X-Amz-Signature=7c7a16fe80f499d542e118cb5a6c9dd8cdbaac7926132f12803f43a051dca524",
    "etiquetas": [
      "Divulgada Correctamente"
    ],
    "needs_download": true
  },
  {
    "publicada": 1,
    "numero": 669,
    "escrutado": true,
    "digitalizado": 1,
    "id_informacion_mesa_corporacion": "010100701007669",
    "nombre_archivo": "https://elecciones-hnd-publicacion-prod-us-east-1.s3.us-east-1.amazonaws.com/E14/01/007/01/007/E14_P01_01_007_001_00_007_669_0242.pdf?X-Amz-Algorithm=AWS4-HMAC-SHA256&X-Amz-Credential=AKIATNSYFO5EYDYMH46K%2F20251206%2Fus-east-1%2Fs3%2Faws4_request&X-Amz-Date=20251206T044050Z&X-Amz-Expires=7200&X-Amz-SignedHeaders=host&X-Amz-Signature=b3494b7e2e2c1d2947d4cdbdd665db8c7cc0edc57ffb5a841cc617e036aaecc4",
    "etiquetas": [
      "Divulgada Correctamente"
    ],
    "needs_download": true
  }
]