[
  {
    "seccion": "I. BALANCE GENERAL",
    "filas": [
      {
        "categoria": "PAPELETAS",
        "subcategoria": "RECIBIDAS SEGÚN ACTA DE APERTURA",
        "digitos": "350",
        "letras": "TRES CINCO CERO",
        "digitosLetras": {
          "numero": "350",
          "letra": [
            "TRES",
            "CINCO",
            "CERO"
          ]
        }
      },
      {
        "categoria": "PAPELETAS",
        "subcategoria": "NO UTILIZADAS/SOBRANTES",
        "digitos": "099",
        "letras": "CERO NUEVE NUEVE",
        "digitosLetras": {
          "numero": "099",
          "letra": [
            "CERO",
            "NUEVE",
            "NUEVE"
          ]
        }
      },
      {
        "categoria": "PAPELETAS",
        "subcategoria": "UTILIZADAS",
        "digitos": "251",
        "letras": "DOS CINCO UNO",
        "digitosLetras": {
          "numero": "251",
          "letra": [
            "DOS",
            "CINCO",
            "UNO"
          ]
        }
      },
      {
        "categoria": "VOTANTES",
        "subcategoria": "CIUDADANOS QUE VOTARON SEGÚN CUADRERO DE VOTACIÓN",
        "digitos": "244",
        "letras": "DOS CUATRO CUATRO",
        "digitosLetras": {
          "numero": "244",
          "letra": [
            "DOS",
            "CUATRO",
            "CUATRO"
          ]
        }
      },
      {
        "categoria": "VOTANTES",
        "subcategoria": "MIEMBROS JRV",
        "digitos": "007",
        "letras": "CERO CERO SIETE",
        "digitosLetras": {
          "numero": "007",
          "letra": [
            "CERO",
            "CERO",
            "SIETE"
          ]
        }
      },
      {
        "categoria": "VOTANTES",
        "subcategoria": "TOTAL VOTANTES",
        "digitos": "251",
        "letras": "DOS CINCO UNO",
        "digitosLetras": {
          "numero": "251",
          "letra": [
            "DOS",
            "CINCO",
            "UNO"
          ]
        }
      }
    ]
  },
  {
    "seccion": "II. RESULTADOS DEL ESCRUTINIO",
    "filas": [
      {
        "categoria": "VOTOS",
        "partido": "PARTIDO DEMÓCRATA CRISTIANO DE HONDURAS (DC)",
        "digitos": "000",
        "letras": "CERO CERO CERO",
        "digitosLetras": {
          "numero": "000",
          "letra": [
            "CERO",
            "CERO",
            "CERO"
          ]
        }
      },
      {
        "categoria": "VOTOS",
        "partido": "PARTIDO LIBERTAD Y REFUNDACIÓN (libre)",
        "digitos": "061",
        "letras": "CERO SEIS UNO",
        "digitosLetras": {
          "numero": "061",
          "letra": [
            "CERO",
            "SEIS",
            "UNO"
          ]
        }
      },
      {
        "categoria": "VOTOS",
        "partido": "PARTIDO INNOVACIÓN Y UNIDAD SOCIAL DEMÓCRATA (PINU)",
        "digitos": "000",
        "letras": "CERO CERO CERO",
        "digitosLetras": {
          "numero": "000",
          "letra": [
            "CERO",
            "CERO",
            "CERO"
          ]
        }
      },
      {
        "categoria": "VOTOS",
        "partido": "PARTIDO LIBERAL DE HONDURAS",
        "digitos": "048",
        "letras": "CERO CUATRO OCHO",
        "digitosLetras": {
          "numero": "048",
          "letra": [
            "CERO",
            "CUATRO",
            "OCHO"
          ]
        }
      },
      {
        "categoria": "VOTOS",
        "partido": "PARTIDO NACIONAL DE HONDURAS",
        "digitos": "133",
        "letras": "UNO TRES TRES",
        "digitosLetras": {
          "numero": "133",
          "letra": [
            "UNO",
            "TRES",
            "TRES"
          ]
        }
      },
      {
        "categoria": "VOTOS",
        "subcategoria": "VOTOS EN BLANCO",
        "digitos": "001",
        "letras": "CERO CERO UNO",
        "digitosLetras": {
          "numero": "001",
          "letra": [
            "CERO",
            "CERO",
            "UNO"
          ]
        }
      },
      {
        "categoria": "VOTOS",
        "subcategoria": "VOTOS NULOS",
        "digitos": "008",
        "letras": "CERO CERO OCHO",
        "digitosLetras": {
          "numero": "008",
          "letra": [
            "CERO",
            "CERO",
            "OCHO"
          ]
        }
      },
      {
        "categoria": "TOTAL",
        "subcategoria": "GRAN TOTAL",
        "digitos": "251",
        "letras": "DOS CINCO UNO",
        "digitosLetras": {
          "numero": "251",
          "letra": [
            "DOS",
            "CINCO",
            "UNO"
          ]
        }
      }
    ]
  }
]