{
  "filings": [
    {
      "section": "I. BALANCE GENERAL",
      "subsections": [
        {
          "subsection": "PAPELETAS",
          "rows": [
            {
              "row": "RECIBIDAS SEGÚN ACTA DE APERTURA",
              "numbers": "336",
              "letters": [
                "tres",
                "tres",
                "seis"
              ]
            },
            {
              "row": "NO UTILIZADAS / SOBRANTES",
              "numbers": "144",
              "letters": [
                "uno",
                "cuatro",
                "cuatro"
              ]
            },
            {
              "row": "UTILIZADAS",
              "numbers": "192",
              "letters": [
                "uno",
                "nueve",
                "dos"
              ]
            }
          ]
        },
        {
          "subsection": "VOTANTES",
          "rows": [
            {
              "row": "CIUDADANOS QUE VOTARON SEGÚN CUADERNO DE VOTACIÓN",
              "numbers": "184",
              "letters": [
                "uno",
                "ocho",
                "cuatro"
              ]
            },
            {
              "row": "MIEMBROS JRV",
              "numbers": "005",
              "letters": [
                "cero",
                "cero",
                "cinco"
              ]
            },
            {
              "row": "CUSTODIOS INFORMÁTICOS ELECTORALES",
              "numbers": "003",
              "letters": [
                "cero",
                "cero",
                "tres"
              ]
            },
            {
              "row": "TOTAL VOTANTES",
              "numbers": "192",
              "letters": [
                "uno",
                "nueve",
                "dos"
              ]
            }
          ]
        }
      ]
    },
    {
      "section": "II. RESULTADOS DEL ESCRUTINIO",
      "rows": [
        {
          "party": "Partido Demócrata Cristiano de Honduras",
          "abbreviation": "DC",
          "numbers": "001",
          "letters": [
            "cero",
            "cero",
            "uno"
          ]
        },
        {
          "party": "Partido Libertad y Refundación",
          "abbreviation": "libre",
          "numbers": "022",
          "letters": [
            "cero",
            "dos",
            "dos"
          ]
        },
        {
          "party": "Partido Innovación y Unidad Social Demócrata",
          "abbreviation": "PINU",
          "numbers": "002",
          "letters": [
            "cero",
            "cero",
            "dos"
          ]
        },
        {
          "party": "Partido Liberal de Honduras",
          "numbers": "131",
          "letters": [
            "uno",
            "tres",
            "uno"
          ]
        },
        {
          "party": "Partido Nacional de Honduras",
          "numbers": "036",
          "letters": [
            "cero",
            "tres",
            "seis"
          ]
        },
        {
          "row": "VOTOS EN BLANCO",
          "numbers": "000",
          "letters": [
            "cero",
            "cero",
            "cero"
          ]
        },
        {
          "row": "VOTOS NULOS",
          "numbers": "000",
          "letters": [
            "cero",
            "cero",
            "cero"
          ]
        },
        {
          "row": "GRAN TOTAL",
          "numbers": "192",
          "letters": [
            "uno",
            "nueve",
            "dos"
          ]
        }
      ]
    }
  ]
}