[
  {
    "publicada": 1,
    "numero": 18932,
    "escrutado": true,
    "digitalizado": 1,
    "id_informacion_mesa_corporacion": "01180070207518932",
    "nombre_archivo": "https://elecciones-hnd-publicacion-prod-us-east-1.s3.us-east-1.amazonaws.com/E14/18/007/02/075/E14_P01_18_007_002_00_075_18932_7567.pdf?X-Amz-Algorithm=AWS4-HMAC-SHA256&X-Amz-Credential=AKIATNSYFO5EYDYMH46K%2F20251206%2Fus-east-1%2Fs3%2Faws4_request&X-Amz-Date=20251206T003926Z&X-Amz-Expires=7200&X-Amz-SignedHeaders=host&X-Amz-Signature=f4e2cb01e7f4e8ed7cf79762b45b07e905f59602400267b8250e4e979c262a38",
    "etiquetas": [
      "Inconsistencia"
    ]
  }
]