{
  "actas": {
    "pendientesVerificacionVisual": 67,
    "total": 684,
    "publicadas": 502,
    "espera": 197,
    "verificacion": 487,
    "inconsistencias": 64,
    "correctas": 438
  },
  "fecha_corte": "2025-12-01 12:26:06.0",
  "depto_code": "02",
  "depto_name": "COLON",
  "candidatos": [
    {
      "cddto_codigo": "000",
      "cddto_nombres": "MARIO ENRIQUE RIVERA CALLEJAS",
      "cddto_apellidos": "",
      "parpo_id": "0001",
      "parpo_nombre": "PARTIDO DEMOCRATA CRISTIANO DE HONDURAS",
      "parpo_color": "#009F3C",
      "parpo_link_logo": "https://elecciones-hnd-publicacion-prod-us-east-1.s3.us-east-1.amazonaws.com/Logos/Partidos/DC.png?X-Amz-Algorithm=AWS4-HMAC-SHA256&X-Amz-Credential=AKIATNSYFO5EYDYMH46K%2F20251203%2Fus-east-1%2Fs3%2Faws4_request&X-Amz-Date=20251203T050417Z&X-Amz-Expires=7200&X-Amz-SignedHeaders=host&X-Amz-Signature=73136f7cb52fb8b4ef988d73ff4072257e5e36dd82577c25295af4db38334324",
      "cddto_link_logo": "https://elecciones-hnd-publicacion-prod-us-east-1.s3.us-east-1.amazonaws.com/Logos/Candidatos/000_0001.png?X-Amz-Algorithm=AWS4-HMAC-SHA256&X-Amz-Credential=AKIATNSYFO5EYDYMH46K%2F20251203%2Fus-east-1%2Fs3%2Faws4_request&X-Amz-Date=20251203T050417Z&X-Amz-Expires=7200&X-Amz-SignedHeaders=host&X-Amz-Signature=943498bbb5413d046c2909be3b8a8939b61199f884c2ec3c1d54dd11f9b5bd68",
      "votos": 134,
      "integrantes": [],
      "parpo_id_int": 1
    },
    {
      "cddto_codigo": "000",
      "cddto_nombres": "RIXI RAMONA MONCADA GODOY",
      "cddto_apellidos": "",
      "parpo_id": "0002",
      "parpo_nombre": "PARTIDO LIBERTAD Y REFUNDACION",
      "parpo_color": "#ff4800",
      "parpo_link_logo": "https://elecciones-hnd-publicacion-prod-us-east-1.s3.us-east-1.amazonaws.com/Logos/Partidos/PARTIDOLIBERTADYREFUNDACION.png?X-Amz-Algorithm=AWS4-HMAC-SHA256&X-Amz-Credential=AKIATNSYFO5EYDYMH46K%2F20251203%2Fus-east-1%2Fs3%2Faws4_request&X-Amz-Date=20251203T050417Z&X-Amz-Expires=7200&X-Amz-SignedHeaders=host&X-Amz-Signature=170168b020c11f8da07dda5af09876e3dbfcecd4ad82a9f63d26d1f34c76a9f0",
      "cddto_link_logo": "https://elecciones-hnd-publicacion-prod-us-east-1.s3.us-east-1.amazonaws.com/Logos/Candidatos/000_0002.png?X-Amz-Algorithm=AWS4-HMAC-SHA256&X-Amz-Credential=AKIATNSYFO5EYDYMH46K%2F20251203%2Fus-east-1%2Fs3%2Faws4_request&X-Amz-Date=20251203T050417Z&X-Amz-Expires=7200&X-Amz-SignedHeaders=host&X-Amz-Signature=1cd875b94f43cbdd8c26be520aaa6657fa9ee065047a3d95f4c101e7d9b03729",
      "votos": 17382,
      "integrantes": [],
      "parpo_id_int": 2
    },
    {
      "cddto_codigo": "000",
      "cddto_nombres": "JORGE NELSON AVILA GUTIERREZ",
      "cddto_apellidos": "",
      "parpo_id": "0003",
      "parpo_nombre": "PARTIDO INNOVACION Y UNIDAD SOCIAL DEMOCRATA",
      "parpo_color": "#F2A900",
      "parpo_link_logo": "https://elecciones-hnd-publicacion-prod-us-east-1.s3.us-east-1.amazonaws.com/Logos/Partidos/PARTIDOINNOVACIONYUNIDADSOCIALDEM%C3%93CRATA.png?X-Amz-Algorithm=AWS4-HMAC-SHA256&X-Amz-Credential=AKIATNSYFO5EYDYMH46K%2F20251203%2Fus-east-1%2Fs3%2Faws4_request&X-Amz-Date=20251203T050417Z&X-Amz-Expires=7200&X-Amz-SignedHeaders=host&X-Amz-Signature=6188ba7fc721f5be87f88d822d38bd56fc1da69e81444b839d5240b8c429d6db",
      "cddto_link_logo": "https://elecciones-hnd-publicacion-prod-us-east-1.s3.us-east-1.amazonaws.com/Logos/Candidatos/000_0003.png?X-Amz-Algorithm=AWS4-HMAC-SHA256&X-Amz-Credential=AKIATNSYFO5EYDYMH46K%2F20251203%2Fus-east-1%2Fs3%2Faws4_request&X-Amz-Date=20251203T050417Z&X-Amz-Expires=7200&X-Amz-SignedHeaders=host&X-Amz-Signature=6dcf5b7b44dec58bdbf33efa833e0e2e51e031a3e068697eb710a50ed40c264d",
      "votos": 430,
      "integrantes": [],
      "parpo_id_int": 3
    },
    {
      "cddto_codigo": "000",
      "cddto_nombres": "SALVADOR ALEJANDRO CESAR NASRALLA SALUM",
      "cddto_apellidos": "",
      "parpo_id": "0004",
      "parpo_nombre": "PARTIDO LIBERAL DE HONDURAS",
      "parpo_color": "#d42225",
      "parpo_link_logo": "https://elecciones-hnd-publicacion-prod-us-east-1.s3.us-east-1.amazonaws.com/Logos/Partidos/PARTIDOLIBERALDEHONDURAS.png?X-Amz-Algorithm=AWS4-HMAC-SHA256&X-Amz-Credential=AKIATNSYFO5EYDYMH46K%2F20251203%2Fus-east-1%2Fs3%2Faws4_request&X-Amz-Date=20251203T050417Z&X-Amz-Expires=7200&X-Amz-SignedHeaders=host&X-Amz-Signature=0423d085e298a37b60b97bccfa08acdd44779bb23b4c3da027cb3188f366d8d3",
      "cddto_link_logo": "https://elecciones-hnd-publicacion-prod-us-east-1.s3.us-east-1.amazonaws.com/Logos/Candidatos/000_0004.png?X-Amz-Algorithm=AWS4-HMAC-SHA256&X-Amz-Credential=AKIATNSYFO5EYDYMH46K%2F20251203%2Fus-east-1%2Fs3%2Faws4_request&X-Amz-Date=20251203T050417Z&X-Amz-Expires=7200&X-Amz-SignedHeaders=host&X-Amz-Signature=5834f16a17e6ed76510a7651f86ecb37fe9310acab8dc85ba0ac381a194150a8",
      "votos": 30401,
      "integrantes": [],
      "parpo_id_int": 4
    },
    {
      "cddto_codigo": "000",
      "cddto_nombres": "NASRY JUAN ASFURA ZABLAH",
      "cddto_apellidos": "",
      "parpo_id": "0005",
      "parpo_nombre": "PARTIDO NACIONAL DE HONDURAS",
      "parpo_color": "#0077C8",
      "parpo_link_logo": "https://elecciones-hnd-publicacion-prod-us-east-1.s3.us-east-1.amazonaws.com/Logos/Partidos/PARTIDONACIONALDEHONDURAS.png?X-Amz-Algorithm=AWS4-HMAC-SHA256&X-Amz-Credential=AKIATNSYFO5EYDYMH46K%2F20251203%2Fus-east-1%2Fs3%2Faws4_request&X-Amz-Date=20251203T050417Z&X-Amz-Expires=7200&X-Amz-SignedHeaders=host&X-Amz-Signature=ae3adfb0141ceae5e87f7224ee201f5bc72980381f5bb6701e51125ea1e35e19",
      "cddto_link_logo": "https://elecciones-hnd-publicacion-prod-us-east-1.s3.us-east-1.amazonaws.com/Logos/Candidatos/000_0005.png?X-Amz-Algorithm=AWS4-HMAC-SHA256&X-Amz-Credential=AKIATNSYFO5EYDYMH46K%2F20251203%2Fus-east-1%2Fs3%2Faws4_request&X-Amz-Date=20251203T050417Z&X-Amz-Expires=7200&X-Amz-SignedHeaders=host&X-Amz-Signature=84978d04f739f82087c20678ac20b9a79e0af8d83a6b1ec1d5642da6c40552af",
      "votos": 25919,
      "integrantes": [],
      "parpo_id_int": 5
    }
  ]
}